pymor/__init__.py
pymor/_version.py
pymor/cli.py
pymor/webapp.py
pymor/core/__init__.py
pymor/core/aux_files.py
pymor/core/caching.py
pymor/core/calendar.py
pymor/core/cluster.py
pymor/core/cmorizer.py
pymor/core/config.py
pymor/core/controlled_vocabularies.py
pymor/core/externals.py
pymor/core/factory.py
pymor/core/filecache.py
pymor/core/frequency.py
pymor/core/gather_inputs.py
pymor/core/logging.py
pymor/core/pipeline.py
pymor/core/plugins.py
pymor/core/rule.py
pymor/core/ssh_tunnel.py
pymor/core/utils.py
pymor/core/validate.py
pymor/data/__init__.py
pymor/data/dimensionless_mappings.yaml
pymor/data/cmip7/__init__.py
pymor/data/cmip7/all_var_info.json
pymor/data_request/__init__.py
pymor/data_request/collection.py
pymor/data_request/table.py
pymor/data_request/variable.py
pymor/dev/__init__.py
pymor/dev/utils.py
pymor/fesom_1p4/__init__.py
pymor/fesom_1p4/load_mesh_data.py
pymor/fesom_1p4/nodes_to_levels.py
pymor/fesom_2p1/__init__.py
pymor/fesom_2p1/regridding.py
pymor/scripts/__init__.py
pymor/scripts/update_dimensionless_mappings.py
pymor/std_lib/__init__.py
pymor/std_lib/dataset_helpers.py
pymor/std_lib/exceptions.py
pymor/std_lib/files.py
pymor/std_lib/generic.py
pymor/std_lib/global_attributes.py
pymor/std_lib/setgrid.py
pymor/std_lib/timeaverage.py
pymor/std_lib/units.py
pymor/std_lib/variable_attributes.py
py_cmor-1.0.1.dist-info/LICENSE
py_cmor-1.0.1.dist-info/METADATA
py_cmor-1.0.1.dist-info/WHEEL
py_cmor-1.0.1.dist-info/entry_points.txt
py_cmor-1.0.1.dist-info/top_level.txt
py_cmor-1.0.1.dist-info/RECORD
