Metadata-Version: 2.1
Name: py-cmor
Version: 1.0.1
Summary: Makes CMOR Simple
Home-page: https://github.com/esm-tools/pymor
Author: Paul Gierz
Author-email: pgierz@awi.de
License: MIT
Classifier: Development Status :: 5 - Production/Stable
Classifier: Programming Language :: Python
Classifier: Programming Language :: Python :: 3
Classifier: Programming Language :: Python :: 3.9
Classifier: Programming Language :: Python :: 3.10
Classifier: Programming Language :: Python :: 3.11
Classifier: Programming Language :: Python :: 3.12
Classifier: Intended Audience :: Science/Research
Classifier: Topic :: Scientific/Engineering
Classifier: Topic :: Scientific/Engineering :: Physics
Classifier: Topic :: Scientific/Engineering :: Atmospheric Science
Classifier: Topic :: Scientific/Engineering :: Oceanography
Requires-Python: >=3.9, <4
License-File: LICENSE
Requires-Dist: bokeh
Requires-Dist: cerberus
Requires-Dist: cf-xarray
Requires-Dist: cftime
Requires-Dist: chemicals
Requires-Dist: click-loguru
Requires-Dist: dask
Requires-Dist: dask-jobqueue
Requires-Dist: deprecation
Requires-Dist: distributed
Requires-Dist: dpath
Requires-Dist: everett[yaml]
Requires-Dist: flexparser<0.4
Requires-Dist: flox
Requires-Dist: h5netcdf
Requires-Dist: imohash
Requires-Dist: joblib
Requires-Dist: netcdf4
Requires-Dist: numbagg
Requires-Dist: numpy
Requires-Dist: pendulum
Requires-Dist: pint-xarray
Requires-Dist: prefect[dask]
Requires-Dist: pyyaml
Requires-Dist: questionary
Requires-Dist: randomname
Requires-Dist: semver>=3.0.4
Requires-Dist: rich-click
Requires-Dist: streamlit
Requires-Dist: tqdm
Requires-Dist: versioneer
Requires-Dist: xarray
Provides-Extra: dev
Requires-Dist: black; extra == "dev"
Requires-Dist: dill; extra == "dev"
Requires-Dist: flake8; extra == "dev"
Requires-Dist: isort; extra == "dev"
Requires-Dist: pooch; extra == "dev"
Requires-Dist: pre-commit; extra == "dev"
Requires-Dist: pyfakefs; extra == "dev"
Requires-Dist: pytest; extra == "dev"
Requires-Dist: pytest-asyncio; extra == "dev"
Requires-Dist: pytest-cov; extra == "dev"
Requires-Dist: pytest-mock; extra == "dev"
Requires-Dist: pytest-xdist; extra == "dev"
Requires-Dist: sphinx; extra == "dev"
Requires-Dist: sphinx-rtd-theme; extra == "dev"
Requires-Dist: yamllint; extra == "dev"
Provides-Extra: doc
Requires-Dist: sphinx-book-theme; extra == "doc"
Requires-Dist: sphinx-click; extra == "doc"
Requires-Dist: sphinx-copybutton; extra == "doc"
Requires-Dist: sphinx-rtd-theme; extra == "doc"
Requires-Dist: sphinx-tabs; extra == "doc"
Requires-Dist: sphinx-toolbox; extra == "doc"
Requires-Dist: sphinx-jinja; extra == "doc"
Requires-Dist: sphinxcontrib-napoleon; extra == "doc"
Requires-Dist: watchdog[watchmedo]; extra == "doc"
Provides-Extra: fesom
Requires-Dist: pyfesom2; extra == "fesom"
